sidan_gin/__init__.py
sidan_gin/encryption/__init__.py
sidan_gin/encryption/cipher.py
sidan_gin/python_signing_module/.git
sidan_gin/python_signing_module/.gitignore
sidan_gin/python_signing_module/.vscode/settings.json
sidan_gin/python_signing_module/Cargo.toml
sidan_gin/python_signing_module/README.md
sidan_gin/python_signing_module/__init__.py
sidan_gin/python_signing_module/build.rs
sidan_gin/python_signing_module/build.sh
sidan_gin/python_signing_module/src/__init__.py
sidan_gin/python_signing_module/src/lib.rs
sidan_gin/python_signing_module/src/setup.py
sidan_gin/python_signing_module/src/signer.cpp
sidan_gin/python_signing_module/src/signer.h
sidan_gin/python_signing_module/src/signer.i
sidan_gin/python_signing_module/src/signer_wrap.cxx
sidan_gin/types/__init__.py
sidan_gin/types/account_info.py
sidan_gin/types/asset.py
sidan_gin/types/asset_metadata.py
sidan_gin/types/block_info.py
sidan_gin/types/network.py
sidan_gin/types/protocol.py
sidan_gin/types/transaction_info.py
sidan_gin/types/utxo.py
sidan_gin/types/value.py
sidan_gin/wallet/__init__.py
sidan_gin/wallet/cli.py
sidan_gin/wallet/derivation_indices.py
sidan_gin/wallet/mnemonic.py
sidan_gin/wallet/root_key.py
sidan_gin/wallet/wallet.py
sidan_gin-0.1.7.dist-info/METADATA
sidan_gin-0.1.7.dist-info/WHEEL
sidan_gin-0.1.7.dist-info/licenses/LICENSE
sidan_gin-0.1.7.dist-info/RECORD
