Metadata-Version: 2.4
Name: sidan-gin
Version: 0.1.7
Summary: A python library for Cardano development, compatible with Mesh and Whisky types.
License: Apache-2.0
License-File: LICENSE
Keywords: cardano
Author: HinsonSIDAN
Author-email: wongkahinhinson@gmail.com
Requires-Python: >3.11,<4.0.0
Classifier: Intended Audience :: Developers
Classifier: License :: OSI Approved :: Apache Software License
Classifier: Natural Language :: English
Classifier: Programming Language :: Python :: 3
Classifier: Programming Language :: Python :: 3.12
Classifier: Programming Language :: Python :: 3.13
Classifier: Programming Language :: Python :: 3.14
Classifier: Programming Language :: Python :: 3.11
Requires-Dist: cardano-python-signing-module (>=0.1.0,<0.2.0)
Requires-Dist: cryptography (>=44.0.2,<45.0.0)
Requires-Dist: pycardano (>=0.12.3,<0.13.0)
Requires-Dist: requests (>=2.25,<3.0)
Project-URL: Documentation, https://github.com/sidan-lab/gin
Project-URL: Homepage, https://github.com/sidan-lab/gin
